src/__init__.py
src/CVE-2021-20323/__init__.py
src/CVE-2021-20323/main.py
src/CVE-2021-20323/includes/__init__.py
src/CVE-2021-20323/includes/bot.py
src/CVE-2021-20323/includes/filereader.py
src/CVE-2021-20323/includes/scan.py
src/CVE-2021-20323/includes/writefile.py
src/CVE-2021-20323/utils/__init__.py
src/CVE-2021-20323/utils/configure.py
src/CVE-2021-20323/utils/const.py
src/CVE-2021-20323/utils/helpers.py
src/CVE_2021_20323/__init__.py
src/CVE_2021_20323/main.py
src/CVE_2021_20323/includes/__init__.py
src/CVE_2021_20323/includes/bot.py
src/CVE_2021_20323/includes/filereader.py
src/CVE_2021_20323/includes/scan.py
src/CVE_2021_20323/includes/writefile.py
src/CVE_2021_20323/utils/__init__.py
src/CVE_2021_20323/utils/configure.py
src/CVE_2021_20323/utils/const.py
src/CVE_2021_20323/utils/helpers.py
CVE_2021_20323-1.1.1.dist-info/METADATA
CVE_2021_20323-1.1.1.dist-info/WHEEL
CVE_2021_20323-1.1.1.dist-info/entry_points.txt
CVE_2021_20323-1.1.1.dist-info/top_level.txt
CVE_2021_20323-1.1.1.dist-info/RECORD
