Metadata-Version: 2.1
Name: CVE-2021-20323
Version: 1.1.1
Summary: A Simple XSS Tool for CVE-2021-20323
Home-page: UNKNOWN
Author: Praveen
Author-email: mspraveenkumar77@gmail.com
License: UNKNOWN
Platform: UNKNOWN
Requires-Dist: PyYAML
Requires-Dist: click
Requires-Dist: requests
Requires-Dist: utils
